rexlex/__init__.py
rexlex/config.py
rexlex/log_config.py
rexlex/utils/__init__.py
rexlex/utils/ansiterm.py
rexlex/lexer/tokentype.py
rexlex/lexer/__init__.py
rexlex/lexer/py2compat.py
rexlex/lexer/utils.py
rexlex/lexer/itemclass.py
rexlex/lexer/exceptions.py
rexlex/lexer/lexer.py
rexlex/lexer/tokendefs.py
rexlex/scanner/scanner.py
rexlex/scanner/__init__.py
rexlex-0.02.dist-info/WHEEL
rexlex-0.02.dist-info/METADATA
rexlex-0.02.dist-info/metadata.json
rexlex-0.02.dist-info/DESCRIPTION.rst
rexlex-0.02.dist-info/top_level.txt
rexlex-0.02.dist-info/RECORD
