Metadata-Version: 2.0
Name: rexlex
Version: 0.02
Summary: Basic regular expression lexer implementation.
Home-page: http://twneale.github.com/rexlex/
Author: Thom Neale
Author-email: twneale@gmail.com
License: MIT
Platform: any
